ou_book_theme/__about__.py
ou_book_theme/__init__.py
ou_book_theme/__main__.py
ou_book_theme/cli/__init__.py
ou_book_theme/extensions/__init__.py
ou_book_theme/extensions/activity.py
ou_book_theme/extensions/errata.py
ou_book_theme/extensions/time.py
ou_book_theme/extensions/video.py
ou_book_theme/extensions/where_next.py
ou_book_theme/latex/Poppins-Bold.ttf
ou_book_theme/latex/Poppins-BoldItalic.ttf
ou_book_theme/latex/Poppins-Italic.ttf
ou_book_theme/latex/Poppins-Regular.ttf
ou_book_theme/latex/ou-book-theme.cls
ou_book_theme/latex/ou-book-theme.sty
ou_book_theme/latex/ou_primary_logo.png
ou_book_theme/theme/ou_book_theme/layout.html
ou_book_theme/theme/ou_book_theme/ou-footer.html
ou_book_theme/theme/ou_book_theme/ou-head.html
ou_book_theme/theme/ou_book_theme/ou-header.html
ou_book_theme/theme/ou_book_theme/theme.conf
ou_book_theme/theme/ou_book_theme/ouheaders/ou-royal-fca-statement.txt
ou_book_theme/theme/ou_book_theme/ouheaders/gui/00.sams
ou_book_theme/theme/ou_book_theme/ouheaders/gui/Accordion_Chevron_Down.png
ou_book_theme/theme/ou_book_theme/ouheaders/gui/Accordion_Chevron_Down.svg
ou_book_theme/theme/ou_book_theme/ouheaders/gui/Accordion_Chevron_Up.png
ou_book_theme/theme/ou_book_theme/ouheaders/gui/Accordion_Chevron_Up.svg
ou_book_theme/theme/ou_book_theme/ouheaders/gui/England.png
ou_book_theme/theme/ou_book_theme/ouheaders/gui/England.svg
ou_book_theme/theme/ou_book_theme/ouheaders/gui/Ireland.png
ou_book_theme/theme/ou_book_theme/ouheaders/gui/Ireland.svg
ou_book_theme/theme/ou_book_theme/ouheaders/gui/OU_Crest_SVG.svg
ou_book_theme/theme/ou_book_theme/ouheaders/gui/OU_Crest_SVG_Mobile.svg
ou_book_theme/theme/ou_book_theme/ouheaders/gui/OU_Logo.svg
ou_book_theme/theme/ou_book_theme/ouheaders/gui/OU_Logo_Ireland.svg
ou_book_theme/theme/ou_book_theme/ouheaders/gui/OU_Logo_Mobile.svg
ou_book_theme/theme/ou_book_theme/ouheaders/gui/OU_Logo_Scotland.svg
ou_book_theme/theme/ou_book_theme/ouheaders/gui/OU_Logo_Wales.svg
ou_book_theme-2.1.0.dist-info/METADATA
ou_book_theme-2.1.0.dist-info/WHEEL
ou_book_theme-2.1.0.dist-info/entry_points.txt
ou_book_theme-2.1.0.dist-info/RECORD
