Metadata-Version: 2.4
Name: ou-book-theme
Version: 2.1.0
Project-URL: Documentation, https://stem-ts-gitlab.open.ac.uk/jupyterhub-infrastructure/ou-book-theme#ou-book-theme
Project-URL: Issues, https://stem-ts-gitlab.open.ac.uk/jupyterhub-infrastructure/ou-book-theme/-/issues
Project-URL: Source, https://stem-ts-gitlab.open.ac.uk/jupyterhub-infrastructure/ou-book-theme
Author-email: Mark Hall <mark.hall@open.ac.uk>
Classifier: Development Status :: 5 - Production/Stable
Classifier: Programming Language :: Python
Classifier: Programming Language :: Python :: 3.10
Classifier: Programming Language :: Python :: 3.11
Classifier: Programming Language :: Python :: 3.12
Classifier: Programming Language :: Python :: 3.13
Classifier: Programming Language :: Python :: Implementation :: CPython
Classifier: Programming Language :: Python :: Implementation :: PyPy
Requires-Python: >=3.10
Requires-Dist: livereload>=2.6.3
Requires-Dist: myst-parser>=4.0.1
Requires-Dist: sphinx-book-theme>=1.0.1
Requires-Dist: sphinx-design>=0.5.0
Requires-Dist: sphinx-external-toc>=1.0.1
Requires-Dist: sphinx>=8
Requires-Dist: sphinxcontrib-mermaid>=0.8.1
Requires-Dist: typer
Requires-Dist: webvtt-py>=0.5.1
